doctranslate
