Metadata-Version: 2.4
Name: doctranslate
Version: 1.5.2
Summary: 文件翻译工具
Requires-Python: >=3.11
License-File: LICENSE
Requires-Dist: httpx==0.27.2
Requires-Dist: jsonpath-ng>=1.7.0
Requires-Dist: openpyxl>=3.1.5
Requires-Dist: xlsx2html>=0.6.2
Requires-Dist: json-repair>=0.48.0
Requires-Dist: mammoth>=1.10.0
Requires-Dist: srt>=3.5.3
Requires-Dist: lxml>=5.4.0
Requires-Dist: python-docx>=1.2.0
Requires-Dist: beautifulsoup4>=4.13.4
Requires-Dist: markdown>=3.8.2
Requires-Dist: pymdown-extensions>=10.16.1
Requires-Dist: chardet>=5.2.0
Requires-Dist: pysubs2>=1.8.0
Provides-Extra: docling
Requires-Dist: opencv-python>=4.11.0.86; extra == "docling"
Requires-Dist: docling>=2.40.0; extra == "docling"
Requires-Dist: hf-xet>=1.1.10; extra == "docling"
Provides-Extra: webui
Requires-Dist: fastapi[standard]>=0.115.12; extra == "webui"
Requires-Dist: uvicorn>=0.30.0; extra == "webui"
Dynamic: license-file
